{
  "points": [
    {
      "latitude": 42.35974,
      "longitude": -71.02733,
      "elevation": 0.0
    },
    {
      "latitude": 42.35976,
      "longitude": -71.02731,
      "elevation": 0.0
    },
    {
      "latitude": 42.36024,
      "longitude": -71.0271,
      "elevation": 0.0
    },
    {
      "latitude": 42.36047,
      "longitude": -71.02702,
      "elevation": 0.0
    },
    {
      "latitude": 42.36194,
      "longitude": -71.02631,
      "elevation": 0.0
    },
    {
      "latitude": 42.36224,
      "longitude": -71.02621,
      "elevation": 0.0
    },
    {
      "latitude": 42.36229,
      "longitude": -71.02619,
      "elevation": 0.0
    },
    {
      "latitude": 42.36311,
      "longitude": -71.02612,
      "elevation": 0.0
    },
    {
      "latitude": 42.36386,
      "longitude": -71.02609,
      "elevation": 0.0
    },
    {
      "latitude": 42.36409,
      "longitude": -71.02612,
      "elevation": 0.0
    },
    {
      "latitude": 42.36424,
      "longitude": -71.02618,
      "elevation": 0.0
    },
    {
      "latitude": 42.3645,
      "longitude": -71.02638,
      "elevation": 0.0
    },
    {
      "latitude": 42.36469,
      "longitude": -71.02662,
      "elevation": 0.0
    },
    {
      "latitude": 42.36482,
      "longitude": -71.02687,
      "elevation": 0.0
    },
    {
      "latitude": 42.36522,
      "longitude": -71.02778,
      "elevation": 0.0
    },
    {
      "latitude": 42.3652,
      "longitude": -71.02779,
      "elevation": 0.0
    },
    {
      "latitude": 42.36523,
      "longitude": -71.02786,
      "elevation": 0.0
    },
    {
      "latitude": 42.36526,
      "longitude": -71.02791,
      "elevation": 0.0
    },
    {
      "latitude": 42.36531,
      "longitude": -71.02787,
      "elevation": 0.0
    },
    {
      "latitude": 42.36531,
      "longitude": -71.02789,
      "elevation": 0.0
    },
    {
      "latitude": 42.36542,
      "longitude": -71.02811,
      "elevation": 0.0
    },
    {
      "latitude": 42.37003,
      "longitude": -71.03864,
      "elevation": 0.0
    },
    {
      "latitude": 42.37003,
      "longitude": -71.03872,
      "elevation": 0.0
    },
    {
      "latitude": 42.37004,
      "longitude": -71.03879,
      "elevation": 0.0
    },
    {
      "latitude": 42.37006,
      "longitude": -71.03884,
      "elevation": 0.0
    },
    {
      "latitude": 42.37006,
      "longitude": -71.03885,
      "elevation": 0.0
    },
    {
      "latitude": 42.37008,
      "longitude": -71.03888,
      "elevation": 0.0
    },
    {
      "latitude": 42.37011,
      "longitude": -71.03892,
      "elevation": 0.0
    },
    {
      "latitude": 42.37015,
      "longitude": -71.03895,
      "elevation": 0.0
    },
    {
      "latitude": 42.37018,
      "longitude": -71.03897,
      "elevation": 0.0
    },
    {
      "latitude": 42.38674,
      "longitude": -71.03931,
      "elevation": 0.0
    },
    {
      "latitude": 42.38789,
      "longitude": -71.03873,
      "elevation": 0.0
    },
    {
      "latitude": 42.38791,
      "longitude": -71.03879,
      "elevation": 0.0
    },
    {
      "latitude": 42.38798,
      "longitude": -71.03903,
      "elevation": 0.0
    },
    {
      "latitude": 42.38827,
      "longitude": -71.0398,
      "elevation": 0.0
    },
    {
      "latitude": 42.38826,
      "longitude": -71.03981,
      "elevation": 0.0
    },
    {
      "latitude": 42.38827,
      "longitude": -71.0398,
      "elevation": 0.0
    },
    {
      "latitude": 42.38932,
      "longitude": -71.03911,
      "elevation": 0.0
    },
    {
      "latitude": 42.38944,
      "longitude": -71.03899,
      "elevation": 0.0
    },
    {
      "latitude": 42.38948,
      "longitude": -71.03894,
      "elevation": 0.0
    },
    {
      "latitude": 42.38951,
      "longitude": -71.03893,
      "elevation": 0.0
    },
    {
      "latitude": 42.38952,
      "longitude": -71.03893,
      "elevation": 0.0
    },
    {
      "latitude": 42.3896,
      "longitude": -71.03894,
      "elevation": 0.0
    },
    {
      "latitude": 42.38963,
      "longitude": -71.03895,
      "elevation": 0.0
    },
    {
      "latitude": 42.40044,
      "longitude": -71.05028,
      "elevation": 0.0
    },
    {
      "latitude": 42.40547,
      "longitude": -71.05699,
      "elevation": 0.0
    },
    {
      "latitude": 42.40545,
      "longitude": -71.057,
      "elevation": 0.0
    },
    {
      "latitude": 42.40501,
      "longitude": -71.05739,
      "elevation": 0.0
    },
    {
      "latitude": 42.40481,
      "longitude": -71.05758,
      "elevation": 0.0
    },
    {
      "latitude": 42.40473,
      "longitude": -71.05767,
      "elevation": 0.0
    },
    {
      "latitude": 42.40456,
      "longitude": -71.05783,
      "elevation": 0.0
    },
    {
      "latitude": 42.40454,
      "longitude": -71.05784,
      "elevation": 0.0
    },
    {
      "latitude": 42.4042,
      "longitude": -71.05817,
      "elevation": 0.0
    },
    {
      "latitude": 42.40416,
      "longitude": -71.0582,
      "elevation": 0.0
    },
    {
      "latitude": 42.4032,
      "longitude": -71.05908,
      "elevation": 0.0
    },
    {
      "latitude": 42.4031,
      "longitude": -71.0592,
      "elevation": 0.0
    },
    {
      "latitude": 42.40298,
      "longitude": -71.05942,
      "elevation": 0.0
    },
    {
      "latitude": 42.40292,
      "longitude": -71.05971,
      "elevation": 0.0
    },
    {
      "latitude": 42.40292,
      "longitude": -71.05988,
      "elevation": 0.0
    },
    {
      "latitude": 42.40295,
      "longitude": -71.06019,
      "elevation": 0.0
    },
    {
      "latitude": 42.40301,
      "longitude": -71.0604,
      "elevation": 0.0
    },
    {
      "latitude": 42.40312,
      "longitude": -71.06059,
      "elevation": 0.0
    },
    {
      "latitude": 42.40309,
      "longitude": -71.06077,
      "elevation": 0.0
    },
    {
      "latitude": 42.40308,
      "longitude": -71.06078,
      "elevation": 0.0
    },
    {
      "latitude": 42.40304,
      "longitude": -71.06092,
      "elevation": 0.0
    },
    {
      "latitude": 42.40288,
      "longitude": -71.061,
      "elevation": 0.0
    },
    {
      "latitude": 42.40275,
      "longitude": -71.06117,
      "elevation": 0.0
    },
    {
      "latitude": 42.40268,
      "longitude": -71.06139,
      "elevation": 0.0
    },
    {
      "latitude": 42.40266,
      "longitude": -71.06153,
      "elevation": 0.0
    },
    {
      "latitude": 42.40268,
      "longitude": -71.06226,
      "elevation": 0.0
    },
    {
      "latitude": 42.40267,
      "longitude": -71.06256,
      "elevation": 0.0
    },
    {
      "latitude": 42.40265,
      "longitude": -71.06287,
      "elevation": 0.0
    },
    {
      "latitude": 42.40261,
      "longitude": -71.06343,
      "elevation": 0.0
    },
    {
      "latitude": 42.40252,
      "longitude": -71.06521,
      "elevation": 0.0
    },
    {
      "latitude": 42.40255,
      "longitude": -71.06584,
      "elevation": 0.0
    },
    {
      "latitude": 42.4026,
      "longitude": -71.06639,
      "elevation": 0.0
    },
    {
      "latitude": 42.40264,
      "longitude": -71.06665,
      "elevation": 0.0
    },
    {
      "latitude": 42.40268,
      "longitude": -71.06664,
      "elevation": 0.0
    },
    {
      "latitude": 42.40273,
      "longitude": -71.06663,
      "elevation": 0.0
    },
    {
      "latitude": 42.40276,
      "longitude": -71.06672,
      "elevation": 0.0
    },
    {
      "latitude": 42.40285,
      "longitude": -71.06728,
      "elevation": 0.0
    },
    {
      "latitude": 42.40285,
      "longitude": -71.06732,
      "elevation": 0.0
    },
    {
      "latitude": 42.40284,
      "longitude": -71.0674,
      "elevation": 0.0
    },
    {
      "latitude": 42.40286,
      "longitude": -71.06755,
      "elevation": 0.0
    },
    {
      "latitude": 42.40287,
      "longitude": -71.06756,
      "elevation": 0.0
    },
    {
      "latitude": 42.40286,
      "longitude": -71.06773,
      "elevation": 0.0
    },
    {
      "latitude": 42.40279,
      "longitude": -71.06807,
      "elevation": 0.0
    },
    {
      "latitude": 42.40278,
      "longitude": -71.06828,
      "elevation": 0.0
    },
    {
      "latitude": 42.4028,
      "longitude": -71.06836,
      "elevation": 0.0
    },
    {
      "latitude": 42.40286,
      "longitude": -71.06844,
      "elevation": 0.0
    },
    {
      "latitude": 42.40308,
      "longitude": -71.06862,
      "elevation": 0.0
    },
    {
      "latitude": 42.40307,
      "longitude": -71.06866,
      "elevation": 0.0
    },
    {
      "latitude": 42.40305,
      "longitude": -71.0687,
      "elevation": 0.0
    },
    {
      "latitude": 42.40312,
      "longitude": -71.06891,
      "elevation": 0.0
    },
    {
      "latitude": 42.40314,
      "longitude": -71.06895,
      "elevation": 0.0
    },
    {
      "latitude": 42.40315,
      "longitude": -71.06896,
      "elevation": 0.0
    },
    {
      "latitude": 42.40317,
      "longitude": -71.06897,
      "elevation": 0.0
    },
    {
      "latitude": 42.40318,
      "longitude": -71.06899,
      "elevation": 0.0
    },
    {
      "latitude": 42.40322,
      "longitude": -71.06911,
      "elevation": 0.0
    },
    {
      "latitude": 42.40324,
      "longitude": -71.06916,
      "elevation": 0.0
    },
    {
      "latitude": 42.40324,
      "longitude": -71.06921,
      "elevation": 0.0
    },
    {
      "latitude": 42.40325,
      "longitude": -71.06926,
      "elevation": 0.0
    },
    {
      "latitude": 42.40326,
      "longitude": -71.06936,
      "elevation": 0.0
    },
    {
      "latitude": 42.40327,
      "longitude": -71.06955,
      "elevation": 0.0
    },
    {
      "latitude": 42.40332,
      "longitude": -71.06981,
      "elevation": 0.0
    },
    {
      "latitude": 42.40356,
      "longitude": -71.07079,
      "elevation": 0.0
    },
    {
      "latitude": 42.40362,
      "longitude": -71.07112,
      "elevation": 0.0
    },
    {
      "latitude": 42.40405,
      "longitude": -71.07312,
      "elevation": 0.0
    },
    {
      "latitude": 42.40409,
      "longitude": -71.07326,
      "elevation": 0.0
    },
    {
      "latitude": 42.40431,
      "longitude": -71.07419,
      "elevation": 0.0
    },
    {
      "latitude": 42.40438,
      "longitude": -71.07439,
      "elevation": 0.0
    },
    {
      "latitude": 42.40439,
      "longitude": -71.07448,
      "elevation": 0.0
    },
    {
      "latitude": 42.4044,
      "longitude": -71.07474,
      "elevation": 0.0
    },
    {
      "latitude": 42.40441,
      "longitude": -71.07479,
      "elevation": 0.0
    },
    {
      "latitude": 42.40445,
      "longitude": -71.07597,
      "elevation": 0.0
    },
    {
      "latitude": 42.40443,
      "longitude": -71.07649,
      "elevation": 0.0
    },
    {
      "latitude": 42.40442,
      "longitude": -71.07741,
      "elevation": 0.0
    },
    {
      "latitude": 42.40444,
      "longitude": -71.07855,
      "elevation": 0.0
    },
    {
      "latitude": 42.40446,
      "longitude": -71.07864,
      "elevation": 0.0
    },
    {
      "latitude": 42.40449,
      "longitude": -71.07872,
      "elevation": 0.0
    },
    {
      "latitude": 42.4045,
      "longitude": -71.07884,
      "elevation": 0.0
    },
    {
      "latitude": 42.40453,
      "longitude": -71.07893,
      "elevation": 0.0
    },
    {
      "latitude": 42.40456,
      "longitude": -71.07896,
      "elevation": 0.0
    },
    {
      "latitude": 42.40455,
      "longitude": -71.07902,
      "elevation": 0.0
    },
    {
      "latitude": 42.40464,
      "longitude": -71.07978,
      "elevation": 0.0
    },
    {
      "latitude": 42.40478,
      "longitude": -71.08047,
      "elevation": 0.0
    },
    {
      "latitude": 42.40491,
      "longitude": -71.08101,
      "elevation": 0.0
    },
    {
      "latitude": 42.40497,
      "longitude": -71.08123,
      "elevation": 0.0
    },
    {
      "latitude": 42.40503,
      "longitude": -71.08133,
      "elevation": 0.0
    },
    {
      "latitude": 42.40501,
      "longitude": -71.08138,
      "elevation": 0.0
    },
    {
      "latitude": 42.40497,
      "longitude": -71.08144,
      "elevation": 0.0
    },
    {
      "latitude": 42.40503,
      "longitude": -71.08159,
      "elevation": 0.0
    },
    {
      "latitude": 42.40507,
      "longitude": -71.08168,
      "elevation": 0.0
    },
    {
      "latitude": 42.40518,
      "longitude": -71.08231,
      "elevation": 0.0
    },
    {
      "latitude": 42.40526,
      "longitude": -71.08234,
      "elevation": 0.0
    },
    {
      "latitude": 42.40533,
      "longitude": -71.08237,
      "elevation": 0.0
    },
    {
      "latitude": 42.4053,
      "longitude": -71.08252,
      "elevation": 0.0
    },
    {
      "latitude": 42.40528,
      "longitude": -71.08264,
      "elevation": 0.0
    },
    {
      "latitude": 42.40524,
      "longitude": -71.08269,
      "elevation": 0.0
    },
    {
      "latitude": 42.40527,
      "longitude": -71.08273,
      "elevation": 0.0
    },
    {
      "latitude": 42.4053,
      "longitude": -71.08278,
      "elevation": 0.0
    },
    {
      "latitude": 42.40527,
      "longitude": -71.0828,
      "elevation": 0.0
    },
    {
      "latitude": 42.40524,
      "longitude": -71.08283,
      "elevation": 0.0
    },
    {
      "latitude": 42.40523,
      "longitude": -71.08289,
      "elevation": 0.0
    },
    {
      "latitude": 42.40519,
      "longitude": -71.08376,
      "elevation": 0.0
    },
    {
      "latitude": 42.40512,
      "longitude": -71.08436,
      "elevation": 0.0
    },
    {
      "latitude": 42.40494,
      "longitude": -71.08518,
      "elevation": 0.0
    },
    {
      "latitude": 42.40488,
      "longitude": -71.08538,
      "elevation": 0.0
    },
    {
      "latitude": 42.40468,
      "longitude": -71.08592,
      "elevation": 0.0
    },
    {
      "latitude": 42.40456,
      "longitude": -71.08627,
      "elevation": 0.0
    },
    {
      "latitude": 42.40449,
      "longitude": -71.0865,
      "elevation": 0.0
    },
    {
      "latitude": 42.40446,
      "longitude": -71.08661,
      "elevation": 0.0
    },
    {
      "latitude": 42.40425,
      "longitude": -71.08767,
      "elevation": 0.0
    },
    {
      "latitude": 42.40424,
      "longitude": -71.08786,
      "elevation": 0.0
    },
    {
      "latitude": 42.40422,
      "longitude": -71.0888,
      "elevation": 0.0
    },
    {
      "latitude": 42.40424,
      "longitude": -71.08894,
      "elevation": 0.0
    },
    {
      "latitude": 42.40429,
      "longitude": -71.0896,
      "elevation": 0.0
    },
    {
      "latitude": 42.4045,
      "longitude": -71.0906,
      "elevation": 0.0
    },
    {
      "latitude": 42.40462,
      "longitude": -71.09101,
      "elevation": 0.0
    },
    {
      "latitude": 42.40482,
      "longitude": -71.09157,
      "elevation": 0.0
    },
    {
      "latitude": 42.40509,
      "longitude": -71.09219,
      "elevation": 0.0
    },
    {
      "latitude": 42.40537,
      "longitude": -71.09278,
      "elevation": 0.0
    },
    {
      "latitude": 42.40563,
      "longitude": -71.09327,
      "elevation": 0.0
    },
    {
      "latitude": 42.40632,
      "longitude": -71.09438,
      "elevation": 0.0
    },
    {
      "latitude": 42.40626,
      "longitude": -71.09444,
      "elevation": 0.0
    },
    {
      "latitude": 42.40632,
      "longitude": -71.09452,
      "elevation": 0.0
    },
    {
      "latitude": 42.40636,
      "longitude": -71.09458,
      "elevation": 0.0
    },
    {
      "latitude": 42.40629,
      "longitude": -71.09466,
      "elevation": 0.0
    },
    {
      "latitude": 42.40609,
      "longitude": -71.09499,
      "elevation": 0.0
    },
    {
      "latitude": 42.40612,
      "longitude": -71.09508,
      "elevation": 0.0
    },
    {
      "latitude": 42.40612,
      "longitude": -71.09534,
      "elevation": 0.0
    },
    {
      "latitude": 42.40611,
      "longitude": -71.09541,
      "elevation": 0.0
    },
    {
      "latitude": 42.40606,
      "longitude": -71.09555,
      "elevation": 0.0
    },
    {
      "latitude": 42.40602,
      "longitude": -71.09578,
      "elevation": 0.0
    },
    {
      "latitude": 42.40599,
      "longitude": -71.09605,
      "elevation": 0.0
    },
    {
      "latitude": 42.4059,
      "longitude": -71.09747,
      "elevation": 0.0
    },
    {
      "latitude": 42.40592,
      "longitude": -71.09774,
      "elevation": 0.0
    },
    {
      "latitude": 42.40595,
      "longitude": -71.09789,
      "elevation": 0.0
    },
    {
      "latitude": 42.406,
      "longitude": -71.09804,
      "elevation": 0.0
    },
    {
      "latitude": 42.40603,
      "longitude": -71.09811,
      "elevation": 0.0
    },
    {
      "latitude": 42.40605,
      "longitude": -71.0982,
      "elevation": 0.0
    },
    {
      "latitude": 42.40609,
      "longitude": -71.09843,
      "elevation": 0.0
    },
    {
      "latitude": 42.4061,
      "longitude": -71.09861,
      "elevation": 0.0
    },
    {
      "latitude": 42.40606,
      "longitude": -71.09866,
      "elevation": 0.0
    },
    {
      "latitude": 42.40601,
      "longitude": -71.09871,
      "elevation": 0.0
    },
    {
      "latitude": 42.40611,
      "longitude": -71.09915,
      "elevation": 0.0
    },
    {
      "latitude": 42.40655,
      "longitude": -71.10067,
      "elevation": 0.0
    },
    {
      "latitude": 42.4066,
      "longitude": -71.10087,
      "elevation": 0.0
    },
    {
      "latitude": 42.40649,
      "longitude": -71.10075,
      "elevation": 0.0
    },
    {
      "latitude": 42.40653,
      "longitude": -71.10094,
      "elevation": 0.0
    },
    {
      "latitude": 42.40655,
      "longitude": -71.10111,
      "elevation": 0.0
    },
    {
      "latitude": 42.40656,
      "longitude": -71.10145,
      "elevation": 0.0
    },
    {
      "latitude": 42.40654,
      "longitude": -71.10177,
      "elevation": 0.0
    },
    {
      "latitude": 42.4065,
      "longitude": -71.10207,
      "elevation": 0.0
    },
    {
      "latitude": 42.40643,
      "longitude": -71.10234,
      "elevation": 0.0
    },
    {
      "latitude": 42.40678,
      "longitude": -71.10266,
      "elevation": 0.0
    },
    {
      "latitude": 42.40688,
      "longitude": -71.10274,
      "elevation": 0.0
    },
    {
      "latitude": 42.40712,
      "longitude": -71.10299,
      "elevation": 0.0
    },
    {
      "latitude": 42.40781,
      "longitude": -71.10365,
      "elevation": 0.0
    },
    {
      "latitude": 42.40802,
      "longitude": -71.10376,
      "elevation": 0.0
    },
    {
      "latitude": 42.40995,
      "longitude": -71.10559,
      "elevation": 0.0
    },
    {
      "latitude": 42.40998,
      "longitude": -71.10561,
      "elevation": 0.0
    },
    {
      "latitude": 42.40935,
      "longitude": -71.10971,
      "elevation": 0.0
    },
    {
      "latitude": 42.40934,
      "longitude": -71.10971,
      "elevation": 0.0
    },
    {
      "latitude": 42.40917,
      "longitude": -71.10965,
      "elevation": 0.0
    },
    {
      "latitude": 42.40946,
      "longitude": -71.11438,
      "elevation": 0.0
    },
    {
      "latitude": 42.40903,
      "longitude": -71.11479,
      "elevation": 0.0
    },
    {
      "latitude": 42.40945,
      "longitude": -71.11438,
      "elevation": 0.0
    },
    {
      "latitude": 42.40946,
      "longitude": -71.11438,
      "elevation": 0.0
    },
    {
      "latitude": 42.40917,
      "longitude": -71.10965,
      "elevation": 0.0
    },
    {
      "latitude": 42.40747,
      "longitude": -71.10889,
      "elevation": 0.0
    },
    {
      "latitude": 42.40568,
      "longitude": -71.10819,
      "elevation": 0.0
    },
    {
      "latitude": 42.40432,
      "longitude": -71.10759,
      "elevation": 0.0
    },
    {
      "latitude": 42.40397,
      "longitude": -71.10741,
      "elevation": 0.0
    },
    {
      "latitude": 42.40354,
      "longitude": -71.10721,
      "elevation": 0.0
    },
    {
      "latitude": 42.40339,
      "longitude": -71.10713,
      "elevation": 0.0
    },
    {
      "latitude": 42.40259,
      "longitude": -71.10677,
      "elevation": 0.0
    },
    {
      "latitude": 42.40242,
      "longitude": -71.10667,
      "elevation": 0.0
    },
    {
      "latitude": 42.4023,
      "longitude": -71.10662,
      "elevation": 0.0
    },
    {
      "latitude": 42.40225,
      "longitude": -71.10659,
      "elevation": 0.0
    },
    {
      "latitude": 42.40206,
      "longitude": -71.10629,
      "elevation": 0.0
    },
    {
      "latitude": 42.4018,
      "longitude": -71.10595,
      "elevation": 0.0
    },
    {
      "latitude": 42.40179,
      "longitude": -71.10594,
      "elevation": 0.0
    },
    {
      "latitude": 42.40113,
      "longitude": -71.10505,
      "elevation": 0.0
    },
    {
      "latitude": 42.40111,
      "longitude": -71.10503,
      "elevation": 0.0
    },
    {
      "latitude": 42.40068,
      "longitude": -71.10444,
      "elevation": 0.0
    },
    {
      "latitude": 42.40036,
      "longitude": -71.10404,
      "elevation": 0.0
    },
    {
      "latitude": 42.39974,
      "longitude": -71.10319,
      "elevation": 0.0
    },
    {
      "latitude": 42.39947,
      "longitude": -71.10285,
      "elevation": 0.0
    },
    {
      "latitude": 42.39926,
      "longitude": -71.10254,
      "elevation": 0.0
    },
    {
      "latitude": 42.39913,
      "longitude": -71.10236,
      "elevation": 0.0
    },
    {
      "latitude": 42.39894,
      "longitude": -71.10207,
      "elevation": 0.0
    },
    {
      "latitude": 42.3984,
      "longitude": -71.1012,
      "elevation": 0.0
    },
    {
      "latitude": 42.39751,
      "longitude": -71.10006,
      "elevation": 0.0
    },
    {
      "latitude": 42.39718,
      "longitude": -71.09969,
      "elevation": 0.0
    },
    {
      "latitude": 42.39712,
      "longitude": -71.09961,
      "elevation": 0.0
    },
    {
      "latitude": 42.39692,
      "longitude": -71.09937,
      "elevation": 0.0
    },
    {
      "latitude": 42.39588,
      "longitude": -71.09826,
      "elevation": 0.0
    },
    {
      "latitude": 42.39556,
      "longitude": -71.09799,
      "elevation": 0.0
    },
    {
      "latitude": 42.39529,
      "longitude": -71.0978,
      "elevation": 0.0
    },
    {
      "latitude": 42.39485,
      "longitude": -71.0976,
      "elevation": 0.0
    },
    {
      "latitude": 42.39474,
      "longitude": -71.09764,
      "elevation": 0.0
    },
    {
      "latitude": 42.3921,
      "longitude": -71.09254,
      "elevation": 0.0
    },
    {
      "latitude": 42.39199,
      "longitude": -71.09236,
      "elevation": 0.0
    },
    {
      "latitude": 42.39187,
      "longitude": -71.09218,
      "elevation": 0.0
    },
    {
      "latitude": 42.3916,
      "longitude": -71.09181,
      "elevation": 0.0
    },
    {
      "latitude": 42.39139,
      "longitude": -71.09154,
      "elevation": 0.0
    },
    {
      "latitude": 42.39085,
      "longitude": -71.09078,
      "elevation": 0.0
    },
    {
      "latitude": 42.39078,
      "longitude": -71.09067,
      "elevation": 0.0
    },
    {
      "latitude": 42.3905,
      "longitude": -71.09014,
      "elevation": 0.0
    },
    {
      "latitude": 42.38953,
      "longitude": -71.08804,
      "elevation": 0.0
    },
    {
      "latitude": 42.38944,
      "longitude": -71.08781,
      "elevation": 0.0
    },
    {
      "latitude": 42.38926,
      "longitude": -71.08739,
      "elevation": 0.0
    },
    {
      "latitude": 42.38923,
      "longitude": -71.08733,
      "elevation": 0.0
    },
    {
      "latitude": 42.38912,
      "longitude": -71.08707,
      "elevation": 0.0
    },
    {
      "latitude": 42.38906,
      "longitude": -71.08695,
      "elevation": 0.0
    },
    {
      "latitude": 42.38879,
      "longitude": -71.08632,
      "elevation": 0.0
    },
    {
      "latitude": 42.38821,
      "longitude": -71.08507,
      "elevation": 0.0
    },
    {
      "latitude": 42.38808,
      "longitude": -71.08476,
      "elevation": 0.0
    },
    {
      "latitude": 42.38781,
      "longitude": -71.08418,
      "elevation": 0.0
    },
    {
      "latitude": 42.38778,
      "longitude": -71.08408,
      "elevation": 0.0
    },
    {
      "latitude": 42.38775,
      "longitude": -71.08401,
      "elevation": 0.0
    },
    {
      "latitude": 42.38755,
      "longitude": -71.08344,
      "elevation": 0.0
    },
    {
      "latitude": 42.3871,
      "longitude": -71.08206,
      "elevation": 0.0
    },
    {
      "latitude": 42.38702,
      "longitude": -71.08174,
      "elevation": 0.0
    },
    {
      "latitude": 42.38674,
      "longitude": -71.08079,
      "elevation": 0.0
    },
    {
      "latitude": 42.38576,
      "longitude": -71.07725,
      "elevation": 0.0
    },
    {
      "latitude": 42.38547,
      "longitude": -71.07661,
      "elevation": 0.0
    },
    {
      "latitude": 42.38539,
      "longitude": -71.07645,
      "elevation": 0.0
    },
    {
      "latitude": 42.38529,
      "longitude": -71.07629,
      "elevation": 0.0
    },
    {
      "latitude": 42.38494,
      "longitude": -71.07568,
      "elevation": 0.0
    },
    {
      "latitude": 42.38479,
      "longitude": -71.07544,
      "elevation": 0.0
    },
    {
      "latitude": 42.38471,
      "longitude": -71.07528,
      "elevation": 0.0
    },
    {
      "latitude": 42.38447,
      "longitude": -71.075,
      "elevation": 0.0
    },
    {
      "latitude": 42.38423,
      "longitude": -71.07469,
      "elevation": 0.0
    },
    {
      "latitude": 42.38421,
      "longitude": -71.07467,
      "elevation": 0.0
    },
    {
      "latitude": 42.38418,
      "longitude": -71.0746,
      "elevation": 0.0
    },
    {
      "latitude": 42.38409,
      "longitude": -71.07444,
      "elevation": 0.0
    },
    {
      "latitude": 42.38408,
      "longitude": -71.07444,
      "elevation": 0.0
    },
    {
      "latitude": 42.38404,
      "longitude": -71.07431,
      "elevation": 0.0
    },
    {
      "latitude": 42.38401,
      "longitude": -71.07419,
      "elevation": 0.0
    },
    {
      "latitude": 42.38398,
      "longitude": -71.0741,
      "elevation": 0.0
    },
    {
      "latitude": 42.38391,
      "longitude": -71.07382,
      "elevation": 0.0
    },
    {
      "latitude": 42.38386,
      "longitude": -71.07365,
      "elevation": 0.0
    },
    {
      "latitude": 42.38386,
      "longitude": -71.07363,
      "elevation": 0.0
    },
    {
      "latitude": 42.38385,
      "longitude": -71.07353,
      "elevation": 0.0
    },
    {
      "latitude": 42.38387,
      "longitude": -71.07333,
      "elevation": 0.0
    },
    {
      "latitude": 42.38394,
      "longitude": -71.07316,
      "elevation": 0.0
    },
    {
      "latitude": 42.38389,
      "longitude": -71.07317,
      "elevation": 0.0
    },
    {
      "latitude": 42.38381,
      "longitude": -71.07319,
      "elevation": 0.0
    },
    {
      "latitude": 42.38377,
      "longitude": -71.07319,
      "elevation": 0.0
    },
    {
      "latitude": 42.38367,
      "longitude": -71.07316,
      "elevation": 0.0
    },
    {
      "latitude": 42.38358,
      "longitude": -71.07312,
      "elevation": 0.0
    },
    {
      "latitude": 42.37847,
      "longitude": -71.0701,
      "elevation": 0.0
    },
    {
      "latitude": 42.37809,
      "longitude": -71.06992,
      "elevation": 0.0
    },
    {
      "latitude": 42.37716,
      "longitude": -71.06937,
      "elevation": 0.0
    },
    {
      "latitude": 42.3768,
      "longitude": -71.06911,
      "elevation": 0.0
    },
    {
      "latitude": 42.37423,
      "longitude": -71.06754,
      "elevation": 0.0
    },
    {
      "latitude": 42.3727,
      "longitude": -71.06414,
      "elevation": 0.0
    },
    {
      "latitude": 42.37244,
      "longitude": -71.06406,
      "elevation": 0.0
    },
    {
      "latitude": 42.37209,
      "longitude": -71.06389,
      "elevation": 0.0
    },
    {
      "latitude": 42.37208,
      "longitude": -71.06388,
      "elevation": 0.0
    },
    {
      "latitude": 42.37209,
      "longitude": -71.06389,
      "elevation": 0.0
    },
    {
      "latitude": 42.37175,
      "longitude": -71.06323,
      "elevation": 0.0
    },
    {
      "latitude": 42.37151,
      "longitude": -71.06262,
      "elevation": 0.0
    },
    {
      "latitude": 42.37143,
      "longitude": -71.06271,
      "elevation": 0.0
    },
    {
      "latitude": 42.3711,
      "longitude": -71.06189,
      "elevation": 0.0
    },
    {
      "latitude": 42.37105,
      "longitude": -71.06178,
      "elevation": 0.0
    },
    {
      "latitude": 42.37101,
      "longitude": -71.06168,
      "elevation": 0.0
    },
    {
      "latitude": 42.37092,
      "longitude": -71.0615,
      "elevation": 0.0
    },
    {
      "latitude": 42.37081,
      "longitude": -71.06133,
      "elevation": 0.0
    },
    {
      "latitude": 42.37055,
      "longitude": -71.06103,
      "elevation": 0.0
    },
    {
      "latitude": 42.37027,
      "longitude": -71.06079,
      "elevation": 0.0
    },
    {
      "latitude": 42.3672,
      "longitude": -71.05865,
      "elevation": 0.0
    },
    {
      "latitude": 42.36702,
      "longitude": -71.05855,
      "elevation": 0.0
    },
    {
      "latitude": 42.36541,
      "longitude": -71.0584,
      "elevation": 0.0
    },
    {
      "latitude": 42.36475,
      "longitude": -71.05838,
      "elevation": 0.0
    },
    {
      "latitude": 42.36466,
      "longitude": -71.05834,
      "elevation": 0.0
    },
    {
      "latitude": 42.36457,
      "longitude": -71.05831,
      "elevation": 0.0
    },
    {
      "latitude": 42.3645,
      "longitude": -71.05829,
      "elevation": 0.0
    },
    {
      "latitude": 42.36445,
      "longitude": -71.05827,
      "elevation": 0.0
    },
    {
      "latitude": 42.36439,
      "longitude": -71.05824,
      "elevation": 0.0
    },
    {
      "latitude": 42.36404,
      "longitude": -71.05788,
      "elevation": 0.0
    },
    {
      "latitude": 42.36394,
      "longitude": -71.0578,
      "elevation": 0.0
    },
    {
      "latitude": 42.36369,
      "longitude": -71.05757,
      "elevation": 0.0
    },
    {
      "latitude": 42.36337,
      "longitude": -71.0572,
      "elevation": 0.0
    },
    {
      "latitude": 42.3633,
      "longitude": -71.05711,
      "elevation": 0.0
    },
    {
      "latitude": 42.3632,
      "longitude": -71.05695,
      "elevation": 0.0
    },
    {
      "latitude": 42.36312,
      "longitude": -71.05683,
      "elevation": 0.0
    },
    {
      "latitude": 42.3631,
      "longitude": -71.05679,
      "elevation": 0.0
    },
    {
      "latitude": 42.36282,
      "longitude": -71.05632,
      "elevation": 0.0
    },
    {
      "latitude": 42.36254,
      "longitude": -71.05582,
      "elevation": 0.0
    },
    {
      "latitude": 42.36206,
      "longitude": -71.05492,
      "elevation": 0.0
    },
    {
      "latitude": 42.362,
      "longitude": -71.05482,
      "elevation": 0.0
    },
    {
      "latitude": 42.36188,
      "longitude": -71.05459,
      "elevation": 0.0
    },
    {
      "latitude": 42.36186,
      "longitude": -71.05454,
      "elevation": 0.0
    },
    {
      "latitude": 42.36183,
      "longitude": -71.05449,
      "elevation": 0.0
    },
    {
      "latitude": 42.36122,
      "longitude": -71.0533,
      "elevation": 0.0
    },
    {
      "latitude": 42.36118,
      "longitude": -71.05321,
      "elevation": 0.0
    },
    {
      "latitude": 42.36115,
      "longitude": -71.05317,
      "elevation": 0.0
    },
    {
      "latitude": 42.36093,
      "longitude": -71.0528,
      "elevation": 0.0
    },
    {
      "latitude": 42.36086,
      "longitude": -71.05272,
      "elevation": 0.0
    },
    {
      "latitude": 42.36083,
      "longitude": -71.05267,
      "elevation": 0.0
    },
    {
      "latitude": 42.36066,
      "longitude": -71.05247,
      "elevation": 0.0
    },
    {
      "latitude": 42.36052,
      "longitude": -71.05233,
      "elevation": 0.0
    },
    {
      "latitude": 42.36035,
      "longitude": -71.05219,
      "elevation": 0.0
    },
    {
      "latitude": 42.36032,
      "longitude": -71.05217,
      "elevation": 0.0
    },
    {
      "latitude": 42.36016,
      "longitude": -71.05205,
      "elevation": 0.0
    },
    {
      "latitude": 42.35993,
      "longitude": -71.05193,
      "elevation": 0.0
    },
    {
      "latitude": 42.35986,
      "longitude": -71.0519,
      "elevation": 0.0
    },
    {
      "latitude": 42.35963,
      "longitude": -71.05181,
      "elevation": 0.0
    },
    {
      "latitude": 42.35971,
      "longitude": -71.05127,
      "elevation": 0.0
    },
    {
      "latitude": 42.35973,
      "longitude": -71.05117,
      "elevation": 0.0
    }
  ]
}